azcam_ascom/__init__.py
azcam_ascom/controller_ascom.py
azcam_ascom/exposure_ascom.py
azcam_ascom/tempcon_ascom.py
azcam_ascom-22.3.2.dist-info/LICENSE
azcam_ascom-22.3.2.dist-info/WHEEL
azcam_ascom-22.3.2.dist-info/METADATA
azcam_ascom-22.3.2.dist-info/RECORD
