Metadata-Version: 2.1
Name: azcam-ascom
Version: 22.3.2
Summary: Azcam extension for ASCOM cameras
Keywords: ccd,imaging,astronomy,sensors
Author: Michael Lesser
Author-email: mlesser@arizona.edu
Requires-Dist: azcam
Requires-Dist: pywin32; sys_platform == 'win32'
Project-URL: Documentation, https://mplesser.github.io/azcam/
Project-URL: Repository, https://github.com/mplesser/azcam-ascom/
